module/__init__.py
ygorganization/__init__.py
ygorganization/asyncquery.py
ygorganization/dbstructure.py
ygorganization_api/__init__.py
ygorganization_api-0.0.1.dev4.dist-info/LICENSE
ygorganization_api-0.0.1.dev4.dist-info/METADATA
ygorganization_api-0.0.1.dev4.dist-info/WHEEL
ygorganization_api-0.0.1.dev4.dist-info/top_level.txt
ygorganization_api-0.0.1.dev4.dist-info/RECORD
