Metadata-Version: 2.1
Name: ygorganization-api
Version: 0.0.1.dev4
Summary: Efficient querying of db.ygorganization.com
Home-page: https://db.ygorganization.com/about/api
Author: gallantron
Author-email: treeston.mmoc@gmail.com
License: UNKNOWN
Platform: UNKNOWN
Classifier: Programming Language :: Python :: 3
Classifier: License :: OSI Approved :: MIT License
Classifier: Operating System :: OS Independent
Requires-Python: >=3.6
